[
    {
        "budget": 35000000,
        "total_cost_used": 35000000.0,
        "total_demand_coverage": 234901676.07086003,
        "total_coverage_percentage": 58.893584938018726
    },
    {
        "budget": 40000000,
        "total_cost_used": 40000000.0,
        "total_demand_coverage": 242885854.38014475,
        "total_coverage_percentage": 60.89534538214728
    },
    {
        "budget": 45000000,
        "total_cost_used": 45000000.0,
        "total_demand_coverage": 256103207.2003683,
        "total_coverage_percentage": 64.20914587941908
    },
    {
        "budget": 50000000,
        "total_cost_used": 50000000.0,
        "total_demand_coverage": 262740987.40584847,
        "total_coverage_percentage": 65.8733429122807
    },
    {
        "budget": 55000000,
        "total_cost_used": 55000000.0,
        "total_demand_coverage": 262999523.71423504,
        "total_coverage_percentage": 65.93816207531185
    },
    {
        "budget": 60000000,
        "total_cost_used": 59950000.0,
        "total_demand_coverage": 262999523.71423504,
        "total_coverage_percentage": 65.93816207531185
    },
    {
        "budget": 65000000,
        "total_cost_used": 64950000.0,
        "total_demand_coverage": 142998248.98872986,
        "total_coverage_percentage": 35.8519345782158
    },
    {
        "budget": 70000000,
        "total_cost_used": 69950000.0,
        "total_demand_coverage": 142998248.98879108,
        "total_coverage_percentage": 35.851934578231145
    },
    {
        "budget": 75000000,
        "total_cost_used": 74950000.0,
        "total_demand_coverage": 142998248.98879272,
        "total_coverage_percentage": 35.85193457823156
    },
    {
        "budget": 80000000,
        "total_cost_used": 79950000.0,
        "total_demand_coverage": 142998248.9888026,
        "total_coverage_percentage": 35.85193457823404
    }
]